zfit_interface/__init__.py
zfit_interface/data.py
zfit_interface/func.py
zfit_interface/pdf.py
zfit_interface/typing.py
zfit_interface/variables.py
zfit_interface/old/__init__.py
zfit_interface/old/data.py
zfit_interface/old/loss.py
zfit_interface/old/minimizer.py
zfit_interface/old/model.py
zfit_interface/old/param.py
zfit_interface/old/result.py
zfit_interface-0.0.3.dist-info/LICENSE
zfit_interface-0.0.3.dist-info/METADATA
zfit_interface-0.0.3.dist-info/WHEEL
zfit_interface-0.0.3.dist-info/top_level.txt
zfit_interface-0.0.3.dist-info/RECORD
